testusecond/__init__.py
testusecond/main.py
testusecond/__system__/imports.py
testusecond/__system__/index.py
testusecond/__system__/modules/jobs.py
testusecond/__system__/sources/clight.json
testusecond/__system__/sources/logo.ico
testusecond-1.0.4.dist-info/METADATA
testusecond-1.0.4.dist-info/WHEEL
testusecond-1.0.4.dist-info/entry_points.txt
testusecond-1.0.4.dist-info/top_level.txt
testusecond-1.0.4.dist-info/RECORD
